sparrow_cvat/__init__.py
sparrow_cvat/__main__.py
sparrow_cvat/api.py
sparrow_cvat/tasks.py
sparrow_cvat/utils.py
sparrow_cvat-1.2.0.dist-info/LICENSE
sparrow_cvat-1.2.0.dist-info/METADATA
sparrow_cvat-1.2.0.dist-info/WHEEL
sparrow_cvat-1.2.0.dist-info/entry_points.txt
sparrow_cvat-1.2.0.dist-info/top_level.txt
sparrow_cvat-1.2.0.dist-info/RECORD
