Metadata-Version: 2.2
Name: sparrow-cvat
Version: 1.2.0
Author: Sparrow Computing
Author-email: ben@sparrow.dev
License-File: LICENSE
Requires-Dist: cvat-sdk==2.15.0
Requires-Dist: fire
Requires-Dist: pillow
Requires-Dist: python-dotenv
Requires-Dist: requests
Requires-Dist: tqdm
Provides-Extra: video
Requires-Dist: opencv-python; extra == "video"
Provides-Extra: dev
Requires-Dist: jupyter; extra == "dev"
Requires-Dist: pytest; extra == "dev"
Requires-Dist: pytest-cov; extra == "dev"
Requires-Dist: uv; extra == "dev"
